{
	"configurations" : 
	[
		{
			"directories" : 
			[
				{
					"build" : ".",
					"minimumCMakeVersion" : 
					{
						"string" : "3.16"
					},
					"projectIndex" : 0,
					"source" : ".",
					"targetIndexes" : 
					[
						0
					]
				}
			],
			"name" : "Debug",
			"projects" : 
			[
				{
					"directoryIndexes" : 
					[
						0
					],
					"name" : "pringlelang",
					"targetIndexes" : 
					[
						0
					]
				}
			],
			"targets" : 
			[
				{
					"directoryIndex" : 0,
					"id" : "pringlelang::@6890427a1f51a3e7e1df",
					"jsonFile" : "target-pringlelang-Debug-2e39a4d7b90277da201a.json",
					"name" : "pringlelang",
					"projectIndex" : 0
				}
			]
		}
	],
	"kind" : "codemodel",
	"paths" : 
	{
		"build" : "/home/solomon/dev/cpp/mcu/reclone/2022-computer-adventures-pringlelang/build",
		"source" : "/home/solomon/dev/cpp/mcu/reclone/2022-computer-adventures-pringlelang"
	},
	"version" : 
	{
		"major" : 2,
		"minor" : 0
	}
}
